{"docs_api_api-list.md":"EgwVo5KZ","docs_api_desc.md":"CsK1zO5w","docs_api_info_depts.md":"De1W1Oo0","docs_api_info_records.md":"CSY1E1JM","docs_scheme_teach.md":"DpUXySvT","docs_product_core_audio.md":"C8315FtO","docs_product_core_auth.md":"BhQwQ0Jy","docs_product_core_call.md":"KY0aB_uc","docs_product_core_enter.md":"CGJzIX8s","docs_product_core_layout.md":"DjdK96Vt","docs_product_core_screen-share.md":"BZnrXFlm","docs_product_core_share.md":"ChaJxAQ2","docs_product_core_video.md":"C7Xr0Zpf","docs_product_intro_desc.md":"DvxpOOFx","docs_product_quickstart_demo.md":"BGORgrY4","docs_product_quickstart_prep.md":"DBigBP_9","docs_scheme_1v1.md":"D5wfiD47","docs_scheme_call.md":"DKqI4e3b","docs_scheme_live.md":"BFvIIQ1E","docs_scheme_meeting.md":"BiQkIFIa","docs_sdk_ios.md":"DFJHr-Ns","docs_sdk_android.md":"0XGUHylj","docs_sdk_windows.md":"BNcIevcJ","docs_sdk_download.md":"CC2cKhSa","docs_api_info_streams.md":"DUXDPqqv","docs_api_info_token.md":"B5bA8lfi","docs_api_info_users.md":"trTVwLee","docs_sdk_applet.md":"D7p9EbUL","docs_sdk_webrtc.md":"BT-iYJD7","docs_sdk_desc.md":"DZyOofDX","docs_product_core_rec.md":"Bd1Z4Hsp","docs_api_info_devices.md":"CEzdoYBq","index.md":"9l7Cg2f_","docs_api_info_servers.md":"Bju9UzpU","docs_api_info_rooms.md":"BiELoXkA"}
